agstuff/__init__.py
agstuff/cards/__init__.py
agstuff/cards/core.py
agstuff/dice/__init__.py
agstuff/dice/core.py
agstuff/dices/__init__.py
agstuff/dices/core.py
agstuff/exceptions/__init__.py
agstuff/exceptions/cards/__init__.py
agstuff/exceptions/cards/card.py
agstuff/exceptions/cards/cards.py
agstuff/exceptions/cards/deck.py
agstuff/validators/__init__.py
agstuff/validators/cards/__init__.py
agstuff/validators/cards/card.py
AGStuff-1.1.0.dist-info/LICENSE
AGStuff-1.1.0.dist-info/METADATA
AGStuff-1.1.0.dist-info/WHEEL
AGStuff-1.1.0.dist-info/top_level.txt
AGStuff-1.1.0.dist-info/RECORD
